hots/__init__.py
hots/cli.py
hots/config/loader.py
hots/core/app.py
hots/core/instance.py
hots/core/interfaces.py
hots/evaluation/evaluator.py
hots/plugins/__init__.py
hots/plugins/clustering/builder.py
hots/plugins/clustering/custom_spectral.py
hots/plugins/clustering/hierarchical.py
hots/plugins/clustering/kmeans.py
hots/plugins/clustering/spectral.py
hots/plugins/connector/file_connector.py
hots/plugins/connector/kafka_connector.py
hots/plugins/optimization/factory.py
hots/plugins/optimization/pyomo_model.py
hots/plugins/problem/__init__.py
hots/plugins/problem/placement.py
hots/utils/logging_config.py
hots/utils/signals.py
hots/utils/tools.py
hots/visualization/plot.py
hots-2.0.2.data/data/VERSION.txt
hots-2.0.2.dist-info/licenses/LICENSE.txt
hots-2.0.2.dist-info/METADATA
hots-2.0.2.dist-info/WHEEL
hots-2.0.2.dist-info/entry_points.txt
hots-2.0.2.dist-info/top_level.txt
hots-2.0.2.dist-info/RECORD
