Metadata-Version: 2.4
Name: hots
Version: 2.0.2
Summary: HOTS: dynamic microservice placement via clustering + optimization
Author-email: Smile R&D team <rnd@smile.fr>
License-Expression: MIT
Project-URL: Homepage, https://github.com/Smile-SA/hots
Project-URL: Documentation, https://hots.readthedocs.io/en/latest/
Keywords: Resource,Optimisation,Clustering,Planning
Platform: any
Classifier: Programming Language :: Python :: 3 :: Only
Classifier: Programming Language :: Python :: 3.10
Classifier: Programming Language :: Python :: Implementation :: CPython
Classifier: Development Status :: 2 - Pre-Alpha
Classifier: Operating System :: POSIX
Classifier: Framework :: Matplotlib
Classifier: Intended Audience :: Science/Research
Classifier: Topic :: Scientific/Engineering :: Information Analysis
Requires-Python: >=3.8
License-File: LICENSE.txt
Requires-Dist: click>=8.0
Requires-Dist: confluent-kafka
Requires-Dist: matplotlib
Requires-Dist: networkx
Requires-Dist: numpy
Requires-Dist: pandas
Requires-Dist: psutil
Requires-Dist: pyomo
Requires-Dist: scikit-learn
Requires-Dist: scipy
Requires-Dist: tqdm
Provides-Extra: dev
Requires-Dist: pytest; extra == "dev"
Requires-Dist: flake8; extra == "dev"
Requires-Dist: flake8-comprehensions; extra == "dev"
Requires-Dist: flake8-docstrings; extra == "dev"
Requires-Dist: flake8-quotes; extra == "dev"
Requires-Dist: flake8-import-order; extra == "dev"
Requires-Dist: pep8-naming; extra == "dev"
Provides-Extra: doc
Requires-Dist: sphinx; extra == "doc"
Provides-Extra: kafka
Requires-Dist: confluent-kafka; extra == "kafka"
Requires-Dist: fastavro; extra == "kafka"
Requires-Dist: requests; extra == "kafka"
Provides-Extra: testing
Requires-Dist: pytest; extra == "testing"
Dynamic: license-file
